PeriodicElements-1.0.dist-info/DESCRIPTION.rst
PeriodicElements-1.0.dist-info/METADATA
PeriodicElements-1.0.dist-info/RECORD
PeriodicElements-1.0.dist-info/WHEEL
PeriodicElements-1.0.dist-info/metadata.json
PeriodicElements-1.0.dist-info/top_level.txt
elements/__init__.py
elements/elements.py
