Metadata-Version: 2.0
Name: PeriodicElements
Version: 1.0
Summary: Periodic Table Elements short description
Home-page: https://github.com/VaasuDevanS/Periodic_Elements
Author: Vaasu Devan S
Author-email: vaasuceg.96@gmail.com
License: GNU-GPL
Platform: UNKNOWN
Classifier: Operating System :: OS Independent
Classifier: Programming Language :: Python
Classifier: Programming Language :: Python :: 2
Classifier: Programming Language :: Python :: 2.6
Classifier: Programming Language :: Python :: 2.7
Classifier: Programming Language :: Python :: 3
Classifier: Programming Language :: Python :: 3.3
Classifier: Programming Language :: Python :: 3.4
Classifier: Programming Language :: Python :: 3.5
Classifier: Programming Language :: Python :: 3.6
